{"id": "ameloblast", "metadata": {"operation": "retrieve", "provider": "Oxford University Press", "schema": "RetrieveEntry"}, "results": [{"id": "ameloblast", "language": "en-gb", "lexicalEntries": [{"entries": [{"etymologies": ["late 19th century; earliest use found in Missouri Dental Journal. From amel + -o- + -blast, after odontoblast"], "pronunciations": [{"phoneticNotation": "IPA", "phoneticSpelling": "\u0259\u02c8m\u025bl\u0259(\u028a)bl\u0251\u02d0st"}, {"phoneticNotation": "IPA", "phoneticSpelling": "\u0259\u02c8m\u025bl\u0259(\u028a)blast"}, {"phoneticNotation": "IPA", "phoneticSpelling": "\u02c8am\u0259l\u0259(\u028a)bl\u0251\u02d0st"}], "senses": [{"definitions": ["A type of epithelial cell responsible for the formation of tooth enamel."], "id": "m_en_gb_oed6289.005", "notes": [{"text": "Formerly also called adamantoblast.", "type": "technicalNote"}]}]}], "language": "en-gb", "lexicalCategory": {"id": "noun", "text": "Noun"}, "text": "ameloblast"}], "type": "headword", "word": "ameloblast"}], "word": "ameloblast"}