{"id": "chlamys", "metadata": {"operation": "retrieve", "provider": "Oxford University Press", "schema": "RetrieveEntry"}, "results": [{"id": "chlamys", "language": "en-us", "lexicalEntries": [{"entries": [{"etymologies": ["late 17th century: from Greek khlamus \u2018cloak\u2019"], "inflections": [{"grammaticalFeatures": [{"id": "plural", "text": "Plural", "type": "Number"}], "inflectedForm": "chlamyses"}, {"grammaticalFeatures": [{"id": "plural", "text": "Plural", "type": "Number"}], "inflectedForm": "chlamydes", "pronunciations": [{"phoneticNotation": "respell", "phoneticSpelling": "\u02c8klam\u0259\u02ccd\u0113z"}]}], "pronunciations": [{"dialects": ["American English"], "phoneticNotation": "respell", "phoneticSpelling": "\u02c8klam\u0259s"}, {"audioFile": "https://audio.oxforddictionaries.com/en/mp3/chlamys_us_1.mp3", "dialects": ["American English"], "phoneticNotation": "IPA", "phoneticSpelling": "\u02c8kl\u00e6m\u0259s"}], "senses": [{"definitions": ["a short cloak worn by men in ancient Greece."], "domainClasses": [{"id": "greek_history", "text": "Greek_History"}, {"id": "clothing", "text": "Clothing"}], "id": "m_en_gbus0178540.008", "semanticClasses": [{"id": "robe", "text": "Robe"}], "shortDefinitions": ["short cloak worn by men in ancient Greece"]}]}], "language": "en-us", "lexicalCategory": {"id": "noun", "text": "Noun"}, "text": "chlamys"}], "type": "headword", "word": "chlamys"}], "word": "chlamys"}