{"id": "commonly", "metadata": {"operation": "retrieve", "provider": "Oxford University Press", "schema": "RetrieveEntry"}, "results": [{"id": "commonly", "language": "en-us", "lexicalEntries": [{"entries": [{"pronunciations": [{"dialects": ["American English"], "phoneticNotation": "respell", "phoneticSpelling": "\u02c8k\u00e4m\u0259nl\u0113"}, {"audioFile": "https://audio.oxforddictionaries.com/en/mp3/commonly_us_1.mp3", "dialects": ["American English"], "phoneticNotation": "IPA", "phoneticSpelling": "\u02c8k\u0251m\u0259nli"}], "senses": [{"definitions": ["very often; frequently"], "examples": [{"text": "a commonly used industrial chemical"}, {"text": "BSE, commonly called mad cow disease"}], "id": "m_en_gbus0204110.005", "shortDefinitions": ["very often"], "synonyms": [{"language": "en", "text": "often"}, {"language": "en", "text": "frequently"}, {"language": "en", "text": "regularly"}, {"language": "en", "text": "repeatedly"}, {"language": "en", "text": "recurrently"}, {"language": "en", "text": "time and again"}, {"language": "en", "text": "time and time again"}, {"language": "en", "text": "over and over"}, {"language": "en", "text": "all the time"}, {"language": "en", "text": "routinely"}, {"language": "en", "text": "habitually"}, {"language": "en", "text": "customarily"}], "thesaurusLinks": [{"entry_id": "commonly", "sense_id": "t_en_gb0002602.001"}]}]}], "language": "en-us", "lexicalCategory": {"id": "adverb", "text": "Adverb"}, "text": "commonly"}], "type": "headword", "word": "commonly"}], "word": "commonly"}