{"id": "docilely", "metadata": {"operation": "retrieve", "provider": "Oxford University Press", "schema": "RetrieveEntry"}, "results": [{"id": "docilely", "language": "en-us", "lexicalEntries": [{"derivativeOf": [{"id": "docile", "text": "docile"}], "entries": [{"pronunciations": [{"dialects": ["American English"], "phoneticNotation": "respell", "phoneticSpelling": "\u02c8d\u00e4s\u0259ll\u0113"}, {"audioFile": "https://audio.oxforddictionaries.com/en/mp3/docilely_us_2.mp3", "dialects": ["American English"], "phoneticNotation": "IPA", "phoneticSpelling": "\u02c8d\u0251s\u0259lli"}], "senses": [{"id": "m_en_gbus0286990.011"}]}], "language": "en-us", "lexicalCategory": {"id": "adverb", "text": "Adverb"}, "text": "docilely"}], "type": "headword", "word": "docilely"}], "word": "docilely"}