{"id": "intersex", "metadata": {"operation": "retrieve", "provider": "Oxford University Press", "schema": "RetrieveEntry"}, "results": [{"id": "intersex", "language": "en-us", "lexicalEntries": [{"entries": [{"pronunciations": [{"dialects": ["American English"], "phoneticNotation": "respell", "phoneticSpelling": "\u02c8in(t)\u0259r\u02ccseks"}, {"audioFile": "https://audio.oxforddictionaries.com/en/mp3/intersex_us_1.mp3", "dialects": ["American English"], "phoneticNotation": "IPA", "phoneticSpelling": "\u02c8\u026an(t)\u0259r\u02ccs\u025bks"}], "senses": [{"definitions": ["relating to or denoting a person or animal that has both male and female sex organs or other sexual characteristics"], "examples": [{"text": "an intersex child"}, {"text": "she identifies as intersex"}], "id": "m_en_gbus0517710.005", "shortDefinitions": ["denoting person or animal that has both male and female sex organs or other sexual characteristics"]}]}], "language": "en-us", "lexicalCategory": {"id": "adjective", "text": "Adjective"}, "text": "intersex"}, {"entries": [{"pronunciations": [{"dialects": ["American English"], "phoneticNotation": "respell", "phoneticSpelling": "\u02c8in(t)\u0259r\u02ccseks"}, {"audioFile": "https://audio.oxforddictionaries.com/en/mp3/intersex_us_1.mp3", "dialects": ["American English"], "phoneticNotation": "IPA", "phoneticSpelling": "\u02c8\u026an(t)\u0259r\u02ccs\u025bks"}], "senses": [{"definitions": ["the condition of having both male and female sex organs or other sexual characteristics"], "domainClasses": [{"id": "biology", "text": "Biology"}, {"id": "medicine", "text": "Medicine"}], "examples": [{"text": "people born with intersex"}], "id": "m_en_gbus0517710.007", "semanticClasses": [{"id": "physiological_state", "text": "Physiological_State"}], "shortDefinitions": ["condition of having both male and female sex organs or other sexual characteristics"], "subsenses": [{"definitions": ["a person or animal having both male and female sex organs or other sexual characteristics"], "domainClasses": [{"id": "medicine", "text": "Medicine"}], "examples": [{"text": "about 1 in 2,000 newborns are intersexes"}], "id": "m_en_gbus0517710.009", "semanticClasses": [{"id": "intersex", "text": "Intersex"}], "shortDefinitions": ["person or animal having both male and female sex organs or other sexual characteristics"]}]}]}], "language": "en-us", "lexicalCategory": {"id": "noun", "text": "Noun"}, "text": "intersex"}], "type": "headword", "word": "intersex"}], "word": "intersex"}