{"id": "jarring", "metadata": {"operation": "retrieve", "provider": "Oxford University Press", "schema": "RetrieveEntry"}, "results": [{"id": "jarring", "language": "en-us", "lexicalEntries": [{"derivatives": [{"id": "jarringly", "text": "jarringly"}], "entries": [{"pronunciations": [{"dialects": ["American English"], "phoneticNotation": "respell", "phoneticSpelling": "\u02c8j\u00e4riNG"}, {"audioFile": "https://audio.oxforddictionaries.com/en/mp3/jarring_us_1.mp3", "dialects": ["American English"], "phoneticNotation": "IPA", "phoneticSpelling": "\u02c8d\u0292\u0251r\u026a\u014b"}], "senses": [{"definitions": ["incongruous in a striking or shocking way; clashing"], "examples": [{"text": "the telephone struck a jarring note in those Renaissance surroundings"}], "id": "m_en_gbus0529480.007", "shortDefinitions": ["incongruous in striking or shocking way"]}, {"definitions": ["causing a physical shock, jolt, or vibration"], "examples": [{"text": "the truck came to a jarring halt"}], "id": "m_en_gbus0529480.009", "shortDefinitions": ["causing physical shock or vibration"]}]}], "language": "en-us", "lexicalCategory": {"id": "adjective", "text": "Adjective"}, "text": "jarring"}], "type": "headword", "word": "jarring"}], "word": "jarring"}