{"id": "jollity", "metadata": {"operation": "retrieve", "provider": "Oxford University Press", "schema": "RetrieveEntry"}, "results": [{"id": "jollity", "language": "en-us", "lexicalEntries": [{"entries": [{"etymologies": ["Middle English: from Old French jolite, from joli (see jolly)"], "inflections": [{"grammaticalFeatures": [{"id": "plural", "text": "Plural", "type": "Number"}], "inflectedForm": "jollities"}], "pronunciations": [{"dialects": ["American English"], "phoneticNotation": "respell", "phoneticSpelling": "\u02c8j\u00e4l\u0259d\u0113"}, {"audioFile": "https://audio.oxforddictionaries.com/en/mp3/jollity_us_1.mp3", "dialects": ["American English"], "phoneticNotation": "IPA", "phoneticSpelling": "\u02c8d\u0292\u0251l\u0259di"}], "senses": [{"definitions": ["lively and cheerful activity or celebration"], "examples": [{"text": "a night of riotous jollity"}], "id": "m_en_gbus0535070.005", "semanticClasses": [{"id": "recreation", "text": "Recreation"}], "shortDefinitions": ["lively and cheerful activity or celebration"], "subsenses": [{"definitions": ["the quality of being cheerful"], "examples": [{"text": "he was full of false jollity"}], "id": "m_en_gbus0535070.008", "semanticClasses": [{"id": "characteristic", "text": "Characteristic"}], "shortDefinitions": ["quality of being cheerful"], "synonyms": [{"language": "en", "text": "vitality"}, {"language": "en", "text": "vigour"}, {"language": "en", "text": "energy"}, {"language": "en", "text": "vivacity"}, {"language": "en", "text": "liveliness"}, {"language": "en", "text": "life"}, {"language": "en", "text": "animation"}, {"language": "en", "text": "sparkle"}, {"language": "en", "text": "effervescence"}, {"language": "en", "text": "exuberance"}, {"language": "en", "text": "verve"}, {"language": "en", "text": "spiritedness"}, {"language": "en", "text": "spirit"}, {"language": "en", "text": "enthusiasm"}, {"language": "en", "text": "dynamism"}, {"language": "en", "text": "fire"}, {"language": "en", "text": "ardour"}, {"language": "en", "text": "zeal"}, {"language": "en", "text": "push"}, {"language": "en", "text": "drive"}], "thesaurusLinks": [{"entry_id": "bounce", "sense_id": "t_en_gb0001650.007"}]}], "synonyms": [{"language": "en", "text": "high spirits"}, {"language": "en", "text": "high-spiritedness"}, {"language": "en", "text": "exuberance"}], "thesaurusLinks": [{"entry_id": "merriment", "sense_id": "t_en_gb0009380.001"}]}]}], "language": "en-us", "lexicalCategory": {"id": "noun", "text": "Noun"}, "text": "jollity"}], "type": "headword", "word": "jollity"}], "word": "jollity"}