{"id": "lugsail", "metadata": {"operation": "retrieve", "provider": "Oxford University Press", "schema": "RetrieveEntry"}, "results": [{"id": "lugsail", "language": "en-us", "lexicalEntries": [{"entries": [{"etymologies": ["late 17th century: probably from lug + the noun sail"], "pronunciations": [{"dialects": ["American English"], "phoneticNotation": "respell", "phoneticSpelling": "\u02c8l\u0259\u0261s\u0259l"}, {"audioFile": "https://audio.oxforddictionaries.com/en/mp3/lugsail_us_1.mp3", "dialects": ["American English"], "phoneticNotation": "IPA", "phoneticSpelling": "\u02c8l\u0259\u0261s\u0259l"}, {"dialects": ["American English"], "phoneticNotation": "respell", "phoneticSpelling": "\u02c8l\u0259\u0261\u02ccs\u0101l"}, {"audioFile": "https://audio.oxforddictionaries.com/en/mp3/lugsail_us_2.mp3", "dialects": ["American English"], "phoneticNotation": "IPA", "phoneticSpelling": "\u02c8l\u0259\u0261\u02ccse\u026al"}], "senses": [{"definitions": ["an asymmetrical four-sided sail that is hoisted on a steeply inclined yard."], "domainClasses": [{"id": "nautical", "text": "Nautical"}], "id": "m_en_gbus0600040.010", "semanticClasses": [{"id": "sail", "text": "Sail"}], "shortDefinitions": ["asymmetrical four-sided sail which is bent on and hoisted from steeply inclined yard"]}]}], "language": "en-us", "lexicalCategory": {"id": "noun", "text": "Noun"}, "text": "lugsail"}], "type": "headword", "word": "lugsail"}], "word": "lugsail"}