{"id": "metaphysicize", "metadata": {"operation": "retrieve", "provider": "Oxford University Press", "schema": "RetrieveEntry"}, "results": [{"id": "metaphysicize", "language": "en-us", "lexicalEntries": [{"derivativeOf": [{"id": "metaphysics", "text": "metaphysics"}], "entries": [{"senses": [{"id": "m_en_gbus0636530.020"}], "variantForms": [{"regions": [{"id": "british", "text": "British"}], "text": "metaphysicise"}]}], "language": "en-us", "lexicalCategory": {"id": "verb", "text": "Verb"}, "text": "metaphysicize"}], "type": "headword", "word": "metaphysicize"}], "word": "metaphysicize"}