{"id": "naughty", "metadata": {"operation": "retrieve", "provider": "Oxford University Press", "schema": "RetrieveEntry"}, "results": [{"id": "naughty", "language": "en-us", "lexicalEntries": [{"derivatives": [{"id": "naughtily", "text": "naughtily"}, {"id": "naughtiness", "text": "naughtiness"}], "entries": [{"etymologies": ["late Middle English: from naught+ -y. The earliest recorded sense was \u2018possessing nothing\u2019; the sense \u2018wicked\u2019 also dates from late Middle English, and gave rise to the current senses"], "inflections": [{"inflectedForm": "naughtier"}, {"inflectedForm": "naughtiest"}], "pronunciations": [{"dialects": ["American English"], "phoneticNotation": "respell", "phoneticSpelling": "\u02c8n\u00f4d\u0113"}, {"audioFile": "https://audio.oxforddictionaries.com/en/mp3/naughty_us_1.mp3", "dialects": ["American English"], "phoneticNotation": "IPA", "phoneticSpelling": "\u02c8n\u0254di"}], "senses": [{"definitions": ["(especially of children) disobedient; badly behaved"], "examples": [{"text": "you've been a really naughty boy"}], "id": "m_en_gbus0680780.008", "shortDefinitions": ["badly behaved"], "synonyms": [{"language": "en", "text": "disobedient"}, {"language": "en", "text": "unruly"}, {"language": "en", "text": "wayward"}, {"language": "en", "text": "errant"}, {"language": "en", "text": "badly behaved"}, {"language": "en", "text": "disorderly"}, {"language": "en", "text": "undisciplined"}, {"language": "en", "text": "delinquent"}, {"language": "en", "text": "troublesome"}, {"language": "en", "text": "rebellious"}, {"language": "en", "text": "defiant"}, {"language": "en", "text": "mutinous"}, {"language": "en", "text": "recalcitrant"}, {"language": "en", "text": "refractory"}, {"language": "en", "text": "uncooperative"}, {"language": "en", "text": "non-compliant"}, {"language": "en", "text": "wilful"}, {"language": "en", "text": "unbiddable"}, {"language": "en", "text": "intractable"}, {"language": "en", "text": "ungovernable"}, {"language": "en", "text": "unmanageable"}, {"language": "en", "text": "uncontrollable"}, {"language": "en", "text": "obstreperous"}, {"language": "en", "text": "awkward"}, {"language": "en", "text": "difficult"}, {"language": "en", "text": "perverse"}, {"language": "en", "text": "contrary"}], "thesaurusLinks": [{"entry_id": "insubordinate", "sense_id": "t_en_gb0008004.001"}]}, {"definitions": ["mildly rude or indecent, typically because related to sex"], "examples": [{"text": "naughty goings-on"}, {"text": "naughty drawings"}], "id": "m_en_gbus0680780.013", "registers": [{"id": "informal", "text": "Informal"}], "shortDefinitions": ["mildly rude or indecent"], "synonyms": [{"language": "en", "text": "indecent"}, {"language": "en", "text": "risqu\u00e9"}, {"language": "en", "text": "rude"}, {"language": "en", "text": "racy"}, {"language": "en", "text": "ribald"}, {"language": "en", "text": "bawdy"}, {"language": "en", "text": "broad"}, {"language": "en", "text": "spicy"}, {"language": "en", "text": "suggestive"}, {"language": "en", "text": "titillating"}, {"language": "en", "text": "improper"}, {"language": "en", "text": "indelicate"}, {"language": "en", "text": "indecorous"}, {"language": "en", "text": "off colour"}], "thesaurusLinks": [{"entry_id": "naughty", "sense_id": "t_en_gb0009874.002"}]}, {"definitions": ["wicked."], "id": "m_en_gbus0680780.015", "registers": [{"id": "archaic", "text": "Archaic"}], "shortDefinitions": ["wicked"], "synonyms": [{"language": "en", "text": "badly behaved"}, {"language": "en", "text": "disobedient"}, {"language": "en", "text": "bad"}, {"language": "en", "text": "misbehaved"}, {"language": "en", "text": "misbehaving"}, {"language": "en", "text": "wayward"}, {"language": "en", "text": "defiant"}, {"language": "en", "text": "unruly"}, {"language": "en", "text": "insubordinate"}, {"language": "en", "text": "wilful"}, {"language": "en", "text": "self-willed"}, {"language": "en", "text": "delinquent"}, {"language": "en", "text": "undisciplined"}, {"language": "en", "text": "unmanageable"}, {"language": "en", "text": "uncontrollable"}, {"language": "en", "text": "ungovernable"}, {"language": "en", "text": "unbiddable"}, {"language": "en", "text": "disorderly"}, {"language": "en", "text": "disruptive"}, {"language": "en", "text": "mutinous"}, {"language": "en", "text": "fractious"}, {"language": "en", "text": "refractory"}, {"language": "en", "text": "recalcitrant"}, {"language": "en", "text": "errant"}, {"language": "en", "text": "wild"}, {"language": "en", "text": "wicked"}, {"language": "en", "text": "obstreperous"}, {"language": "en", "text": "difficult"}, {"language": "en", "text": "troublesome"}, {"language": "en", "text": "awkward"}, {"language": "en", "text": "contrary"}, {"language": "en", "text": "perverse"}, {"language": "en", "text": "attention-seeking"}, {"language": "en", "text": "exasperating"}, {"language": "en", "text": "incorrigible"}], "thesaurusLinks": [{"entry_id": "naughty", "sense_id": "t_en_gb0009874.001"}]}]}], "language": "en-us", "lexicalCategory": {"id": "adjective", "text": "Adjective"}, "text": "naughty"}], "type": "headword", "word": "naughty"}], "word": "naughty"}