{"id": "overbank", "metadata": {"operation": "retrieve", "provider": "Oxford University Press", "schema": "RetrieveEntry"}, "results": [{"id": "overbank", "language": "en-gb", "lexicalEntries": [{"entries": [{"etymologies": ["early 20th century; earliest use found in Arthur William Judge (b. 1887). From overbank"], "homographNumber": "100", "pronunciations": [{"phoneticNotation": "IPA", "phoneticSpelling": "\u02c8\u0259\u028av\u0259ba\u014bk"}], "senses": [{"definitions": ["The action or an act of overbanking."], "domains": [{"id": "aeronautics", "text": "Aeronautics"}], "id": "m_en_gb_oed134284.003"}]}], "language": "en-gb", "lexicalCategory": {"id": "noun", "text": "Noun"}, "text": "overbank"}], "type": "headword", "word": "overbank"}, {"id": "overbank", "language": "en-gb", "lexicalEntries": [{"entries": [{"etymologies": ["mid 17th century; earliest use found in Samuel Rutherford (c1600\u20131661), Church of Scotland minister and political theorist. From over- + bank"], "homographNumber": "200", "pronunciations": [{"phoneticNotation": "IPA", "phoneticSpelling": "\u02c8\u0259\u028av\u0259ba\u014bk"}], "senses": [{"definitions": ["That is over or above the bank (of a river, etc.); that overflows or has overflowed the edge of a river bank."], "id": "m_en_gb_oed134285.004", "notes": [{"text": "In later use Physical Geography and Hydrology.", "type": "technicalNote"}]}, {"definitions": ["Designating or relating to a kind of gun carriage for muzzle-loading guns which enables the gun to be fired over a parapet."], "id": "m_en_gb_oed134285.007", "registers": [{"id": "historical", "text": "Historical"}, {"id": "rare", "text": "Rare"}]}]}], "language": "en-gb", "lexicalCategory": {"id": "adjective", "text": "Adjective"}, "text": "overbank"}], "type": "headword", "word": "overbank"}, {"id": "overbank", "language": "en-gb", "lexicalEntries": [{"entries": [{"etymologies": ["mid 19th century (in an earlier sense). From over- + bank"], "homographNumber": "300", "pronunciations": [{"phoneticNotation": "IPA", "phoneticSpelling": "\u02cc\u0259\u028av\u0259\u02c8ba\u014bk"}], "senses": [{"definitions": ["To bank (an aircraft) too much when making a turn; to bank too much in the performance of (a turn)."], "domains": [{"id": "aeronautics", "text": "Aeronautics"}], "id": "m_en_gb_oed134286.004"}, {"definitions": ["Of an aircraft or its pilot: to bank too much."], "id": "m_en_gb_oed134286.006"}]}], "language": "en-gb", "lexicalCategory": {"id": "verb", "text": "Verb"}, "text": "overbank"}], "type": "headword", "word": "overbank"}, {"id": "overbank", "language": "en-gb", "lexicalEntries": [{"entries": [{"etymologies": ["early 20th century; earliest use found in The American Economic Review. From over- + bank"], "homographNumber": "400", "pronunciations": [{"phoneticNotation": "IPA", "phoneticSpelling": "\u02cc\u0259\u028av\u0259\u02c8ba\u014bk"}], "senses": [{"definitions": ["To found or provide too many banks or banking facilities in (a place)."], "domains": [{"id": "finance", "text": "Finance"}], "id": "m_en_gb_oed257910.003"}]}], "language": "en-gb", "lexicalCategory": {"id": "verb", "text": "Verb"}, "text": "overbank"}], "type": "headword", "word": "overbank"}], "word": "overbank"}