{"id": "pittancer", "metadata": {"operation": "retrieve", "provider": "Oxford University Press", "schema": "RetrieveEntry"}, "results": [{"id": "pittancer", "language": "en-gb", "lexicalEntries": [{"entries": [{"etymologies": ["late Middle English. From pittance + -er, after Middle French pitancier"], "pronunciations": [{"phoneticNotation": "IPA", "phoneticSpelling": "\u02c8p\u026at(\u0259)ns\u0259"}], "senses": [{"definitions": ["An officer in a religious house having the duty of distributing and accounting for pittances."], "id": "m_en_gb_oed144785.003", "registers": [{"id": "historical", "text": "Historical"}]}]}], "language": "en-gb", "lexicalCategory": {"id": "noun", "text": "Noun"}, "text": "pittancer"}], "type": "headword", "word": "pittancer"}], "word": "pittancer"}