{"id": "praefervid", "metadata": {"operation": "retrieve", "provider": "Oxford University Press", "schema": "RetrieveEntry"}, "results": [{"id": "praefervid", "language": "en-gb", "lexicalEntries": [{"entries": [{"etymologies": ["early 18th century; earliest use found in John Lauder (1646\u20131722), judge and political commentator. From classical Latin praefervidus exceedingly hot, burning, impassioned, especially in the post-classical Latin phrase Scotorum praefervida ingenia impassioned genius of the Scots from prae- + fervidus"], "pronunciations": [{"phoneticNotation": "IPA", "phoneticSpelling": "pri\u02d0\u02c8f\u0259\u02d0v\u026ad"}], "senses": [{"definitions": ["perfervid."], "id": "m_en_gb_oed149256.003"}], "variantForms": [{"text": "prefervid"}]}], "language": "en-gb", "lexicalCategory": {"id": "adjective", "text": "Adjective"}, "text": "praefervid"}], "type": "headword", "word": "praefervid"}], "word": "praefervid"}