{"id": "prosthesis", "metadata": {"operation": "retrieve", "provider": "Oxford University Press", "schema": "RetrieveEntry"}, "results": [{"id": "prosthesis", "language": "en-us", "lexicalEntries": [{"entries": [{"etymologies": ["mid 16th century (in prosthesis (sense 2)): via late Latin from Greek prosthesis, from prostithenai, from pros \u2018in addition\u2019 + tithenai \u2018to place\u2019"], "inflections": [{"grammaticalFeatures": [{"id": "plural", "text": "Plural", "type": "Number"}], "inflectedForm": "prostheses", "pronunciations": [{"phoneticNotation": "respell", "phoneticSpelling": "-s\u0113z"}]}], "pronunciations": [{"dialects": ["American English"], "phoneticNotation": "respell", "phoneticSpelling": "pr\u00e4s\u02c8TH\u0113sis"}, {"audioFile": "https://audio.oxforddictionaries.com/en/mp3/prosthesis_us_1.mp3", "dialects": ["American English"], "phoneticNotation": "IPA", "phoneticSpelling": "pr\u0251s\u02c8\u03b8is\u026as"}], "senses": [{"definitions": ["an artificial body part, such as a leg, a heart, or a breast implant"], "domainClasses": [{"id": "surgery", "text": "Surgery"}], "examples": [{"text": "his upper jaw was removed and a prosthesis was fitted"}], "id": "m_en_gbus0822650.009", "semanticClasses": [{"id": "prosthesis", "text": "Prosthesis"}], "shortDefinitions": ["artificial body part, such as limb"]}, {"definitions": ["the addition of a letter or syllable at the beginning of a word, as in Spanish escribo derived from Latin scribo."], "domainClasses": [{"id": "linguistics", "text": "Linguistics"}, {"id": "grammar", "text": "Grammar"}], "domains": [{"id": "linguistics", "text": "Linguistics"}], "id": "m_en_gbus0822650.015", "notes": [{"text": "also \"prothesis\"", "type": "wordFormNote"}], "semanticClasses": [{"id": "linguistic_process", "text": "Linguistic_Process"}], "shortDefinitions": ["addition of letter or syllable at beginning of word"]}]}], "language": "en-us", "lexicalCategory": {"id": "noun", "text": "Noun"}, "text": "prosthesis"}], "type": "headword", "word": "prosthesis"}], "word": "prosthesis"}