{"id": "rejoiceful", "metadata": {"operation": "retrieve", "provider": "Oxford University Press", "schema": "RetrieveEntry"}, "results": [{"id": "rejoiceful", "language": "en-gb", "lexicalEntries": [{"entries": [{"etymologies": ["mid 16th century; earliest use found in Thomas Elyot (c1490\u20131546), humanist and diplomat. From rejoice + -ful"], "pronunciations": [{"phoneticNotation": "IPA", "phoneticSpelling": "r\u026a\u02c8d\u0292\u0254\u026asf(\u028a)l"}], "senses": [{"definitions": ["Full of or characterized by rejoicing; joyful, joyous."], "id": "m_en_gb_oed161738.003", "registers": [{"id": "rare", "text": "Rare"}]}]}], "language": "en-gb", "lexicalCategory": {"id": "adjective", "text": "Adjective"}, "text": "rejoiceful"}], "type": "headword", "word": "rejoiceful"}], "word": "rejoiceful"}