{"id": "rifleman", "metadata": {"operation": "retrieve", "provider": "Oxford University Press", "schema": "RetrieveEntry"}, "results": [{"id": "rifleman", "language": "en-us", "lexicalEntries": [{"entries": [{"inflections": [{"grammaticalFeatures": [{"id": "plural", "text": "Plural", "type": "Number"}], "inflectedForm": "riflemen"}], "pronunciations": [{"dialects": ["American English"], "phoneticNotation": "respell", "phoneticSpelling": "\u02c8r\u012bf\u0259lm\u0259n"}, {"audioFile": "https://audio.oxforddictionaries.com/en/mp3/rifleman_us_1.mp3", "dialects": ["American English"], "phoneticNotation": "IPA", "phoneticSpelling": "\u02c8ra\u026af\u0259lm\u0259n"}], "senses": [{"definitions": ["a soldier armed with a rifle, especially a private in a rifle regiment."], "domainClasses": [{"id": "military", "text": "Military"}], "id": "m_en_gbus0873310.008", "semanticClasses": [{"id": "soldier", "text": "Soldier"}], "shortDefinitions": ["soldier armed with rifle"], "subsenses": [{"definitions": ["a person skilled at using a rifle."], "domainClasses": [{"id": "military", "text": "Military"}], "id": "m_en_gbus0873310.011", "semanticClasses": [{"id": "soldier", "text": "Soldier"}], "shortDefinitions": ["person skilled at using rifle"]}], "synonyms": [{"language": "en", "text": "marksman"}, {"language": "en", "text": "markswoman"}, {"language": "en", "text": "shooter"}, {"language": "en", "text": "rifleman"}], "thesaurusLinks": [{"entry_id": "shot", "sense_id": "t_en_gb0013408.004"}]}, {"definitions": ["a very small, short-tailed, greenish-yellow songbird which feeds on insects on tree bark, native to New Zealand."], "domainClasses": [{"id": "bird", "text": "Bird"}], "etymologies": ["perhaps so named from a comparison between its plumage and an early military uniform"], "id": "m_en_gbus0873310.013", "notes": [{"text": "Acanthisitta chloris, family Xenicidae", "type": "technicalNote"}], "semanticClasses": [{"id": "passerine", "text": "Passerine"}], "shortDefinitions": ["very small, short-tailed, greenish-yellow songbird"]}]}], "language": "en-us", "lexicalCategory": {"id": "noun", "text": "Noun"}, "text": "rifleman"}], "type": "headword", "word": "rifleman"}], "word": "rifleman"}