{"id": "sacramentalist", "metadata": {"operation": "retrieve", "provider": "Oxford University Press", "schema": "RetrieveEntry"}, "results": [{"id": "sacramentalist", "language": "en-us", "lexicalEntries": [{"derivativeOf": [{"id": "sacramental", "text": "sacramental"}], "entries": [{"senses": [{"id": "m_en_gbus0891680.018"}]}], "language": "en-us", "lexicalCategory": {"id": "noun", "text": "Noun"}, "text": "sacramentalist"}], "type": "headword", "word": "sacramentalist"}], "word": "sacramentalist"}