{"id": "shouse", "metadata": {"operation": "retrieve", "provider": "Oxford University Press", "schema": "RetrieveEntry"}, "results": [{"id": "shouse", "language": "en-gb", "lexicalEntries": [{"entries": [{"etymologies": ["1940s; earliest use found in Sidney Baker (1912\u20131976). Shortened from shithouse"], "pronunciations": [{"phoneticNotation": "IPA", "phoneticSpelling": "\u0283a\u028as"}], "senses": [{"definitions": ["A toilet (especially an outdoor one); = \"shithouse\"."], "id": "m_en_gb_oed178704.003", "regions": [{"id": "australian", "text": "Australian"}], "registers": [{"id": "slang", "text": "Slang"}]}], "variantForms": [{"text": "s'house"}, {"text": "sh'ouse"}, {"text": "shoush"}]}], "language": "en-gb", "lexicalCategory": {"id": "noun", "text": "Noun"}, "text": "shouse"}], "type": "headword", "word": "shouse"}], "word": "shouse"}