{"id": "sleety", "metadata": {"operation": "retrieve", "provider": "Oxford University Press", "schema": "RetrieveEntry"}, "results": [{"id": "sleety", "language": "en-us", "lexicalEntries": [{"derivativeOf": [{"id": "sleet", "text": "sleet"}], "entries": [{"pronunciations": [{"dialects": ["American English"], "phoneticNotation": "respell", "phoneticSpelling": "\u02c8sl\u0113d\u0113"}, {"audioFile": "https://audio.oxforddictionaries.com/en/mp3/sleety_us_1.mp3", "dialects": ["American English"], "phoneticNotation": "IPA", "phoneticSpelling": "\u02c8slidi"}], "senses": [{"id": "m_en_gbus0954760.020"}]}], "language": "en-us", "lexicalCategory": {"id": "adjective", "text": "Adjective"}, "text": "sleety"}], "type": "headword", "word": "sleety"}], "word": "sleety"}