{"id": "subcommissioner", "metadata": {"operation": "retrieve", "provider": "Oxford University Press", "schema": "RetrieveEntry"}, "results": [{"id": "subcommissioner", "language": "en-gb", "lexicalEntries": [{"entries": [{"etymologies": ["early 17th century. From sub- + commissioner"], "pronunciations": [{"phoneticNotation": "IPA", "phoneticSpelling": "\u02ccs\u028cbk\u0259\u02c8m\u026a\u0283(\u0259)n\u0259"}, {"phoneticNotation": "IPA", "phoneticSpelling": "\u02ccs\u028cbk\u0259\u02c8m\u026a\u0283(\u0259)n\u0259"}], "senses": [{"definitions": ["A subordinate commissioner; especially a person serving as deputy or assistant to a commissioner."], "id": "m_en_gb_oed192521.004"}]}], "language": "en-gb", "lexicalCategory": {"id": "noun", "text": "Noun"}, "text": "subcommissioner"}], "type": "headword", "word": "subcommissioner"}], "word": "subcommissioner"}