{"id": "undramatic", "metadata": {"operation": "retrieve", "provider": "Oxford University Press", "schema": "RetrieveEntry"}, "results": [{"id": "undramatic", "language": "en-us", "lexicalEntries": [{"entries": [{"pronunciations": [{"dialects": ["American English"], "phoneticNotation": "respell", "phoneticSpelling": "\u02cc\u0259ndr\u0259\u02c8madik"}, {"audioFile": "https://audio.oxforddictionaries.com/en/mp3/undramatic_us_1.mp3", "dialects": ["American English"], "phoneticNotation": "IPA", "phoneticSpelling": "\u02cc\u0259ndr\u0259\u02c8m\u00e6d\u026ak"}], "senses": [{"definitions": ["lacking the qualities expected in drama"], "examples": [{"text": "an undramatic libretto"}], "id": "m_en_gbus1098190.005", "shortDefinitions": ["lacking qualities expected in drama"], "subsenses": [{"definitions": ["unexciting"], "examples": [{"text": "research tends to be undramatic and unglamorous"}], "id": "m_en_gbus1098190.007", "shortDefinitions": ["unexciting"]}]}]}], "language": "en-us", "lexicalCategory": {"id": "adjective", "text": "Adjective"}, "text": "undramatic"}], "type": "headword", "word": "undramatic"}], "word": "undramatic"}