{"metadata": {"provider": "Oxford University Press"}, "results": [{"id": "preestablished", "language": "en", "lexicalEntries": [{"inflectionOf": [{"id": "pre-established", "text": "pre-established"}], "language": "en", "lexicalCategory": {"id": "adjective", "text": "Adjective"}, "text": "preestablished"}, {"inflectionOf": [{"id": "preestablish", "text": "preestablish"}], "language": "en", "lexicalCategory": {"id": "verb", "text": "Verb"}, "text": "preestablished"}, {"inflectionOf": [{"id": "preestablished", "text": "preestablished"}], "language": "en", "lexicalCategory": {"id": "adjective", "text": "Adjective"}, "text": "preestablished"}, {"inflectionOf": [{"id": "pre-establish", "text": "pre-establish"}], "language": "en", "lexicalCategory": {"id": "verb", "text": "Verb"}, "text": "preestablished"}], "word": "preestablished"}]}