{"metadata": {"provider": "Oxford University Press"}, "results": [{"id": "reflowering", "language": "en", "lexicalEntries": [{"inflectionOf": [{"id": "reflowering", "text": "reflowering"}], "language": "en", "lexicalCategory": {"id": "adjective", "text": "Adjective"}, "text": "reflowering"}, {"inflectionOf": [{"id": "reflowering", "text": "reflowering"}], "language": "en", "lexicalCategory": {"id": "noun", "text": "Noun"}, "text": "reflowering"}, {"inflectionOf": [{"id": "reflower", "text": "reflower"}], "language": "en", "lexicalCategory": {"id": "verb", "text": "Verb"}, "text": "reflowering"}], "word": "reflowering"}]}